mutalyzer_spdi_parser/__init__.py
mutalyzer_spdi_parser/cli.py
mutalyzer_spdi_parser/convert.py
mutalyzer_spdi_parser/spdi_parser.py
mutalyzer_spdi_parser/ebnf/top.g
mutalyzer_spdi_parser-0.3.1.dist-info/LICENSE
mutalyzer_spdi_parser-0.3.1.dist-info/METADATA
mutalyzer_spdi_parser-0.3.1.dist-info/WHEEL
mutalyzer_spdi_parser-0.3.1.dist-info/entry_points.txt
mutalyzer_spdi_parser-0.3.1.dist-info/top_level.txt
mutalyzer_spdi_parser-0.3.1.dist-info/RECORD
