Metadata-Version: 2.1
Name: mutalyzer_spdi_parser
Version: 0.3.1
Summary: Mutalyzer SPDI variant description parser.
Home-page: https://github.com/mutalyzer/spdi-parser
Author: Mihai Lefter
Author-email: M.Lefter@lumc.nl
License: MIT
Keywords: Mutalyzer,HGVS,SPDI,description,parser,genomic
Classifier: Programming Language :: Python :: 3.6
Classifier: Programming Language :: Python :: 3.7
Classifier: Programming Language :: Python :: 3.8
Classifier: Programming Language :: Python :: 3.9
Classifier: Programming Language :: Python :: 3.10
License-File: LICENSE
Requires-Dist: lark >=1.0.0
Provides-Extra: test
Requires-Dist: pytest ; extra == 'test'
